Workbook

Sheet README
A1: Polska 2040 — model finansowy v0.1
A2: Niezależny draft — nie jest prognozą budżetową ani ofertą inwestycyjną
A4: Zasada nadrzędna | B4: Wartość brakująca nie jest zerem. Status UNKNOWN pozostaje widoczny, a formuły nie zwracają sumy, dopóki wymagany składnik jest nieznany.
A5: Jednostka kosztowa | B5: mln PLN w cenach roku bazowego wskazanego przy każdym założeniu; waluta źródłowa i kurs mają osobne rekordy.
A6: Scenariusze | B6: L — integracja niskokosztowa; B — portfel bazowy; H — przyspieszona mobilizacja. To warianty decyzji, nie przedziały ufności.
A7: Kolor niebieski | B7: Komórka wejściowa do uzupełnienia wyłącznie po wpisaniu źródła/claimu, statusu, właściciela i daty ważności.
A8: Kolor żółty | B8: UNKNOWN albo wymagany plan pozyskania; nie zastępować wartością modelową bez decyzji o założeniu.
A9: Źródła | B9: Każde wejście wskazuje CLM-####, SRC-#### albo identyfikator zatwierdzonej decyzji/założenia. Arkusz nie jest samodzielnym źródłem faktu.
A10: Podwójne finansowanie | B10: Ten sam koszt ma jeden Cost ID. Legalne współfinansowanie ujawnia udziały; dwóch instrumentów nie wolno liczyć jako dwóch rezultatów.
A11: Wynik | B11: Model pokazuje zobowiązania, płatności, ekspozycje warunkowe, TCO, dodatkowość, wpływ i wrażliwość. Publikacja wymaga niezależnej walidacji.

Sheet Assumptions
A1: ID | B1: Cost ID | C1: Parametr / założenie | D1: Status | E1: L | F1: B | G1: H | H1: Jednostka | I1: Rok cen | J1: Claim / źródło | K1: Właściciel | L1: Ważne do | M1: Wrażliwość | N1: Plan pozyskania / uwagi
A2: ASM-001 | B2: C01 | C2: Przyrostowy koszt governance i ewaluacji | D2: UNKNOWN | H2: mln PLN | I2: UNKNOWN | J2: UNKNOWN | K2: do wskazania | L2: UNKNOWN | M2: do oceny | N2: Wymagany audyt bazowy i zatwierdzone założenie.
A3: ASM-002 | B3: C02 | C3: Koszt katalogu problemów, testów i małych partii | D3: UNKNOWN | H3: mln PLN | I3: UNKNOWN | J3: UNKNOWN | K3: do wskazania | L3: UNKNOWN | M3: do oceny | N3: Wymagany audyt bazowy i zatwierdzone założenie.
A4: ASM-003 | B4: C03 | C4: Koszt przestrzeni danych, AI i obliczeń | D4: UNKNOWN | H4: mln PLN | I4: UNKNOWN | J4: UNKNOWN | K4: do wskazania | L4: UNKNOWN | M4: do oceny | N4: Wymagany audyt bazowy i zatwierdzone założenie.
A5: ASM-004 | B5: C04 | C5: Koszt cyber i bezpiecznego cyklu software | D5: UNKNOWN | H5: mln PLN | I5: UNKNOWN | J5: UNKNOWN | K5: do wskazania | L5: UNKNOWN | M5: do oceny | N5: Wymagany audyt bazowy i zatwierdzone założenie.
A6: ASM-005 | B6: C05 | C6: Przyrostowy CAPEX przemysłowy i komponentowy | D6: UNKNOWN | H6: mln PLN | I6: UNKNOWN | J6: UNKNOWN | K6: do wskazania | L6: UNKNOWN | M6: do oceny | N6: Wymagany audyt bazowy i zatwierdzone założenie.
A7: ASM-006 | B7: C06 | C7: Koszt serwisu, logistyki, części i utylizacji | D7: UNKNOWN | H7: mln PLN | I7: UNKNOWN | J7: UNKNOWN | K7: do wskazania | L7: UNKNOWN | M7: do oceny | N7: Wymagany audyt bazowy i zatwierdzone założenie.
A8: ASM-007 | B8: C07 | C8: Koszt kadr, praktyk i programów kompetencji | D8: UNKNOWN | H8: mln PLN | I8: UNKNOWN | J8: UNKNOWN | K8: do wskazania | L8: UNKNOWN | M8: do oceny | N8: Wymagany audyt bazowy i zatwierdzone założenie.
A9: ASM-008 | B9: C08 | C9: Koszt partnerstw, IP, due diligence i certyfikacji | D9: UNKNOWN | H9: mln PLN | I9: UNKNOWN | J9: UNKNOWN | K9: do wskazania | L9: UNKNOWN | M9: do oceny | N9: Wymagany audyt bazowy i zatwierdzone założenie.
A10: ASM-009 | B10: C09 | C10: Koszt pilotaży regionalnych i cywilnych | D10: UNKNOWN | H10: mln PLN | I10: UNKNOWN | J10: UNKNOWN | K10: do wskazania | L10: UNKNOWN | M10: do oceny | N10: Wymagany audyt bazowy i zatwierdzone założenie.
A11: ASM-010 | B11: C10 | C11: Koszt instrumentów eksportu i obsługi rynków | D11: UNKNOWN | H11: mln PLN | I11: UNKNOWN | J11: UNKNOWN | K11: do wskazania | L11: UNKNOWN | M11: do oceny | N11: Wymagany audyt bazowy i zatwierdzone założenie.
A12: ASM-011 | B12: X01 | C12: Istniejące zobowiązania w zakresie programu | D12: UNKNOWN | H12: mln PLN | I12: UNKNOWN | J12: UNKNOWN | K12: do wskazania | L12: UNKNOWN | M12: do oceny | N12: Wymagany audyt bazowy i zatwierdzone założenie.
A13: ASM-012 | B13: X02 | C13: Koszt obsługi finansowania pożyczkowego | D13: UNKNOWN | H13: mln PLN | I13: UNKNOWN | J13: UNKNOWN | K13: do wskazania | L13: UNKNOWN | M13: do oceny | N13: Wymagany audyt bazowy i zatwierdzone założenie.
... A16: ASM-015 | B16: X05 | C16: Udział kosztów dodatkowych względem bazowej aktywności | D16: UNKNOWN | H16: mln PLN | I16: UNKNOWN | J16: UNKNOWN | K16: do wskazania | L16: UNKNOWN | M16: do oceny | N16: Wymagany audyt bazowy i zatwierdzone założenie.

Sheet Commitments
A1: Cost ID | B1: Project ID | C1: Opis kosztu | D1: Instrument | E1: Status | F1: Rok zobowiązania | G1: Rok płatności | H1: Kwota mln PLN | I1: Udział krajowy | J1: Udział UE/inny | K1: Waluta źródłowa | L1: Claim / źródło | M1: Dodatkowość | N1: Ryzyko kolizji | O1: Uwagi / sposób rozstrzygnięcia
A2: COST-001 | B2: UNKNOWN | C2: UNKNOWN | D2: do przypisania | E2: UNKNOWN | F2: UNKNOWN | G2: UNKNOWN | K2: PLN | L2: UNKNOWN | M2: do oceny | N2: do oceny
A3: COST-002 | B3: UNKNOWN | C3: UNKNOWN | D3: do przypisania | E3: UNKNOWN | F3: UNKNOWN | G3: UNKNOWN | K3: PLN | L3: UNKNOWN | M3: do oceny | N3: do oceny
A4: COST-003 | B4: UNKNOWN | C4: UNKNOWN | D4: do przypisania | E4: UNKNOWN | F4: UNKNOWN | G4: UNKNOWN | K4: PLN | L4: UNKNOWN | M4: do oceny | N4: do oceny
A5: COST-004 | B5: UNKNOWN | C5: UNKNOWN | D5: do przypisania | E5: UNKNOWN | F5: UNKNOWN | G5: UNKNOWN | K5: PLN | L5: UNKNOWN | M5: do oceny | N5: do oceny
A6: COST-005 | B6: UNKNOWN | C6: UNKNOWN | D6: do przypisania | E6: UNKNOWN | F6: UNKNOWN | G6: UNKNOWN | K6: PLN | L6: UNKNOWN | M6: do oceny | N6: do oceny
A7: COST-006 | B7: UNKNOWN | C7: UNKNOWN | D7: do przypisania | E7: UNKNOWN | F7: UNKNOWN | G7: UNKNOWN | K7: PLN | L7: UNKNOWN | M7: do oceny | N7: do oceny
A8: COST-007 | B8: UNKNOWN | C8: UNKNOWN | D8: do przypisania | E8: UNKNOWN | F8: UNKNOWN | G8: UNKNOWN | K8: PLN | L8: UNKNOWN | M8: do oceny | N8: do oceny
A9: COST-008 | B9: UNKNOWN | C9: UNKNOWN | D9: do przypisania | E9: UNKNOWN | F9: UNKNOWN | G9: UNKNOWN | K9: PLN | L9: UNKNOWN | M9: do oceny | N9: do oceny
A10: COST-009 | B10: UNKNOWN | C10: UNKNOWN | D10: do przypisania | E10: UNKNOWN | F10: UNKNOWN | G10: UNKNOWN | K10: PLN | L10: UNKNOWN | M10: do oceny | N10: do oceny
A11: COST-010 | B11: UNKNOWN | C11: UNKNOWN | D11: do przypisania | E11: UNKNOWN | F11: UNKNOWN | G11: UNKNOWN | K11: PLN | L11: UNKNOWN | M11: do oceny | N11: do oceny
A12: COST-011 | B12: UNKNOWN | C12: UNKNOWN | D12: do przypisania | E12: UNKNOWN | F12: UNKNOWN | G12: UNKNOWN | K12: PLN | L12: UNKNOWN | M12: do oceny | N12: do oceny
A13: COST-012 | B13: UNKNOWN | C13: UNKNOWN | D13: do przypisania | E13: UNKNOWN | F13: UNKNOWN | G13: UNKNOWN | K13: PLN | L13: UNKNOWN | M13: do oceny | N13: do oceny
... A26: COST-025 | B26: UNKNOWN | C26: UNKNOWN | D26: do przypisania | E26: UNKNOWN | F26: UNKNOWN | G26: UNKNOWN | K26: PLN | L26: UNKNOWN | M26: do oceny | N26: do oceny

Sheet Cost model
A1: Cost ID | B1: Kategoria | C1: L | D1: B | E1: H | F1: Reguła
A2: C01 | B2: Governance i ewaluacja | C2: =IF(COUNTIFS(Assumptions!$B$2:$B$100,$A2,Assumptions!$D$2:$D$100,"UNKNOWN")>0,"UNKNOWN",SUMIFS(Assumptions!$E$2:$E$100,Assumptions!$B$2:$B$100,$A2)) -> UNKNOWN | D2: =IF(COUNTIFS(Assumptions!$B$2:$B$100,$A2,Assumptions!$D$2:$D$100,"UNKNOWN")>0,"UNKNOWN",SUMIFS(Assumptions!$F$2:$F$100,Assumptions!$B$2:$B$100,$A2)) -> UNKNOWN | E2: =IF(COUNTIFS(Assumptions!$B$2:$B$100,$A2,Assumptions!$D$2:$D$100,"UNKNOWN")>0,"UNKNOWN",SUMIFS(Assumptions!$G$2:$G$100,Assumptions!$B$2:$B$100,$A2)) -> UNKNOWN | F2: UNKNOWN propaguje się do wyniku; zero wymaga jawnego założenia FACT/ASSUMPTION.
A3: C02 | B3: Problemy, testy i małe partie | C3: =IF(COUNTIFS(Assumptions!$B$2:$B$100,$A3,Assumptions!$D$2:$D$100,"UNKNOWN")>0,"UNKNOWN",SUMIFS(Assumptions!$E$2:$E$100,Assumptions!$B$2:$B$100,$A3)) -> UNKNOWN | D3: =IF(COUNTIFS(Assumptions!$B$2:$B$100,$A3,Assumptions!$D$2:$D$100,"UNKNOWN")>0,"UNKNOWN",SUMIFS(Assumptions!$F$2:$F$100,Assumptions!$B$2:$B$100,$A3)) -> UNKNOWN | E3: =IF(COUNTIFS(Assumptions!$B$2:$B$100,$A3,Assumptions!$D$2:$D$100,"UNKNOWN")>0,"UNKNOWN",SUMIFS(Assumptions!$G$2:$G$100,Assumptions!$B$2:$B$100,$A3)) -> UNKNOWN | F3: UNKNOWN propaguje się do wyniku; zero wymaga jawnego założenia FACT/ASSUMPTION.
A4: C03 | B4: Dane, AI i obliczenia | C4: =IF(COUNTIFS(Assumptions!$B$2:$B$100,$A4,Assumptions!$D$2:$D$100,"UNKNOWN")>0,"UNKNOWN",SUMIFS(Assumptions!$E$2:$E$100,Assumptions!$B$2:$B$100,$A4)) -> UNKNOWN | D4: =IF(COUNTIFS(Assumptions!$B$2:$B$100,$A4,Assumptions!$D$2:$D$100,"UNKNOWN")>0,"UNKNOWN",SUMIFS(Assumptions!$F$2:$F$100,Assumptions!$B$2:$B$100,$A4)) -> UNKNOWN | E4: =IF(COUNTIFS(Assumptions!$B$2:$B$100,$A4,Assumptions!$D$2:$D$100,"UNKNOWN")>0,"UNKNOWN",SUMIFS(Assumptions!$G$2:$G$100,Assumptions!$B$2:$B$100,$A4)) -> UNKNOWN | F4: UNKNOWN propaguje się do wyniku; zero wymaga jawnego założenia FACT/ASSUMPTION.
A5: C04 | B5: Cyber i software | C5: =IF(COUNTIFS(Assumptions!$B$2:$B$100,$A5,Assumptions!$D$2:$D$100,"UNKNOWN")>0,"UNKNOWN",SUMIFS(Assumptions!$E$2:$E$100,Assumptions!$B$2:$B$100,$A5)) -> UNKNOWN | D5: =IF(COUNTIFS(Assumptions!$B$2:$B$100,$A5,Assumptions!$D$2:$D$100,"UNKNOWN")>0,"UNKNOWN",SUMIFS(Assumptions!$F$2:$F$100,Assumptions!$B$2:$B$100,$A5)) -> UNKNOWN | E5: =IF(COUNTIFS(Assumptions!$B$2:$B$100,$A5,Assumptions!$D$2:$D$100,"UNKNOWN")>0,"UNKNOWN",SUMIFS(Assumptions!$G$2:$G$100,Assumptions!$B$2:$B$100,$A5)) -> UNKNOWN | F5: UNKNOWN propaguje się do wyniku; zero wymaga jawnego założenia FACT/ASSUMPTION.
A6: C05 | B6: Przemysł i komponenty | C6: =IF(COUNTIFS(Assumptions!$B$2:$B$100,$A6,Assumptions!$D$2:$D$100,"UNKNOWN")>0,"UNKNOWN",SUMIFS(Assumptions!$E$2:$E$100,Assumptions!$B$2:$B$100,$A6)) -> UNKNOWN | D6: =IF(COUNTIFS(Assumptions!$B$2:$B$100,$A6,Assumptions!$D$2:$D$100,"UNKNOWN")>0,"UNKNOWN",SUMIFS(Assumptions!$F$2:$F$100,Assumptions!$B$2:$B$100,$A6)) -> UNKNOWN | E6: =IF(COUNTIFS(Assumptions!$B$2:$B$100,$A6,Assumptions!$D$2:$D$100,"UNKNOWN")>0,"UNKNOWN",SUMIFS(Assumptions!$G$2:$G$100,Assumptions!$B$2:$B$100,$A6)) -> UNKNOWN | F6: UNKNOWN propaguje się do wyniku; zero wymaga jawnego założenia FACT/ASSUMPTION.
A7: C06 | B7: Serwis i logistyka | C7: =IF(COUNTIFS(Assumptions!$B$2:$B$100,$A7,Assumptions!$D$2:$D$100,"UNKNOWN")>0,"UNKNOWN",SUMIFS(Assumptions!$E$2:$E$100,Assumptions!$B$2:$B$100,$A7)) -> UNKNOWN | D7: =IF(COUNTIFS(Assumptions!$B$2:$B$100,$A7,Assumptions!$D$2:$D$100,"UNKNOWN")>0,"UNKNOWN",SUMIFS(Assumptions!$F$2:$F$100,Assumptions!$B$2:$B$100,$A7)) -> UNKNOWN | E7: =IF(COUNTIFS(Assumptions!$B$2:$B$100,$A7,Assumptions!$D$2:$D$100,"UNKNOWN")>0,"UNKNOWN",SUMIFS(Assumptions!$G$2:$G$100,Assumptions!$B$2:$B$100,$A7)) -> UNKNOWN | F7: UNKNOWN propaguje się do wyniku; zero wymaga jawnego założenia FACT/ASSUMPTION.
A8: C07 | B8: Kadry i edukacja | C8: =IF(COUNTIFS(Assumptions!$B$2:$B$100,$A8,Assumptions!$D$2:$D$100,"UNKNOWN")>0,"UNKNOWN",SUMIFS(Assumptions!$E$2:$E$100,Assumptions!$B$2:$B$100,$A8)) -> UNKNOWN | D8: =IF(COUNTIFS(Assumptions!$B$2:$B$100,$A8,Assumptions!$D$2:$D$100,"UNKNOWN")>0,"UNKNOWN",SUMIFS(Assumptions!$F$2:$F$100,Assumptions!$B$2:$B$100,$A8)) -> UNKNOWN | E8: =IF(COUNTIFS(Assumptions!$B$2:$B$100,$A8,Assumptions!$D$2:$D$100,"UNKNOWN")>0,"UNKNOWN",SUMIFS(Assumptions!$G$2:$G$100,Assumptions!$B$2:$B$100,$A8)) -> UNKNOWN | F8: UNKNOWN propaguje się do wyniku; zero wymaga jawnego założenia FACT/ASSUMPTION.
A9: C08 | B9: Partnerstwa, IP i certyfikacja | C9: =IF(COUNTIFS(Assumptions!$B$2:$B$100,$A9,Assumptions!$D$2:$D$100,"UNKNOWN")>0,"UNKNOWN",SUMIFS(Assumptions!$E$2:$E$100,Assumptions!$B$2:$B$100,$A9)) -> UNKNOWN | D9: =IF(COUNTIFS(Assumptions!$B$2:$B$100,$A9,Assumptions!$D$2:$D$100,"UNKNOWN")>0,"UNKNOWN",SUMIFS(Assumptions!$F$2:$F$100,Assumptions!$B$2:$B$100,$A9)) -> UNKNOWN | E9: =IF(COUNTIFS(Assumptions!$B$2:$B$100,$A9,Assumptions!$D$2:$D$100,"UNKNOWN")>0,"UNKNOWN",SUMIFS(Assumptions!$G$2:$G$100,Assumptions!$B$2:$B$100,$A9)) -> UNKNOWN | F9: UNKNOWN propaguje się do wyniku; zero wymaga jawnego założenia FACT/ASSUMPTION.
A10: C09 | B10: Regiony i zastosowania cywilne | C10: =IF(COUNTIFS(Assumptions!$B$2:$B$100,$A10,Assumptions!$D$2:$D$100,"UNKNOWN")>0,"UNKNOWN",SUMIFS(Assumptions!$E$2:$E$100,Assumptions!$B$2:$B$100,$A10)) -> UNKNOWN | D10: =IF(COUNTIFS(Assumptions!$B$2:$B$100,$A10,Assumptions!$D$2:$D$100,"UNKNOWN")>0,"UNKNOWN",SUMIFS(Assumptions!$F$2:$F$100,Assumptions!$B$2:$B$100,$A10)) -> UNKNOWN | E10: =IF(COUNTIFS(Assumptions!$B$2:$B$100,$A10,Assumptions!$D$2:$D$100,"UNKNOWN")>0,"UNKNOWN",SUMIFS(Assumptions!$G$2:$G$100,Assumptions!$B$2:$B$100,$A10)) -> UNKNOWN | F10: UNKNOWN propaguje się do wyniku; zero wymaga jawnego założenia FACT/ASSUMPTION.
A11: C10 | B11: Eksport | C11: =IF(COUNTIFS(Assumptions!$B$2:$B$100,$A11,Assumptions!$D$2:$D$100,"UNKNOWN")>0,"UNKNOWN",SUMIFS(Assumptions!$E$2:$E$100,Assumptions!$B$2:$B$100,$A11)) -> UNKNOWN | D11: =IF(COUNTIFS(Assumptions!$B$2:$B$100,$A11,Assumptions!$D$2:$D$100,"UNKNOWN")>0,"UNKNOWN",SUMIFS(Assumptions!$F$2:$F$100,Assumptions!$B$2:$B$100,$A11)) -> UNKNOWN | E11: =IF(COUNTIFS(Assumptions!$B$2:$B$100,$A11,Assumptions!$D$2:$D$100,"UNKNOWN")>0,"UNKNOWN",SUMIFS(Assumptions!$G$2:$G$100,Assumptions!$B$2:$B$100,$A11)) -> UNKNOWN | F11: UNKNOWN propaguje się do wyniku; zero wymaga jawnego założenia FACT/ASSUMPTION.
A12: TOTAL | B12: SUMA PRZYROSTOWA | C12: =IF(COUNTIF(C2:C11,"UNKNOWN")>0,"UNKNOWN",SUM(C2:C11)) -> UNKNOWN | D12: =IF(COUNTIF(D2:D11,"UNKNOWN")>0,"UNKNOWN",SUM(D2:D11)) -> UNKNOWN | E12: =IF(COUNTIF(E2:E11,"UNKNOWN")>0,"UNKNOWN",SUM(E2:E11)) -> UNKNOWN | F12: Suma nie obejmuje istniejących zobowiązań ani kosztu finansowania, dopóki nie zostaną osobno zmapowane.

Sheet Funding map
A1: Instrument | B1: Etap/ryzyko | C1: Potencjalna funkcja | D1: Status analizy | E1: Współfinansowanie | F1: Podwójne finansowanie | G1: Claim / źródło | H1: Warunek użycia / zastrzeżenie
A2: Budżet państwa | B2: zadania publiczne i zakupy | C2: mandat, usługi, kontrakty | D2: do mapowania | E2: zależne od pozycji | F2: wysokie | G2: UNKNOWN | H2: Wskazać dysponenta, zobowiązanie, płatność i koszt alternatywny.
A3: SAFE | B3: zdolności i zamówienia | C3: finansowanie pożyczkowe | D3: umowa podpisana | E3: do weryfikacji | F3: wysokie | G3: CLM-1208/1209 | H3: Nie traktować 43,7 mld EUR jako dotacji ani całej kwoty nowego programu; kwalifikowalność per koszt.
A4: EDF | B4: B+R i demonstracja | C4: projekty konsorcjalne | D4: do weryfikacji call | E4: zależne od call | F4: wysokie | G4: UNKNOWN | H4: Sprawdzić bieżący regulamin, IP, konsorcjum i koszty kwalifikowane.
A5: EUDIS | B5: innowacje i scale-up | C5: instrument zależny od ścieżki | D5: do weryfikacji | E5: zależne | F5: średnie | G5: UNKNOWN | H5: Nie zakładać dostępności ani kwalifikowalności bez aktualnego naboru.
A6: STEP | B6: technologie strategiczne | C6: platforma/oznaczenie i instrumenty powiązane | D6: do weryfikacji | E6: zależne | F6: wysokie | G6: UNKNOWN | H6: Wskazać konkretny program finansujący, nie liczyć całej platformy.
A7: PFR/BGK | B7: kapitał, kredyt, gwarancja | C7: moce i kapitał obrotowy | D7: do mapowania | E7: zależne | F7: średnie | G7: UNKNOWN | H7: Prywatny udział ryzyka, wycena ekspozycji i strategia wyjścia.
A8: NCBR/PARP | B8: B+R, MŚP, internacjonalizacja | C8: granty i programy | D8: do mapowania | E8: zależne | F8: wysokie | G8: UNKNOWN | H8: Połączyć z użytkownikiem i bramką wdrożeniową; nie dublować kosztu.
A9: Kapitał prywatny | B9: ryzyko rynkowe i skala | C9: equity/debt/strategic | D9: case-by-case | E9: nie dotyczy | F9: niskie/średnie | G9: UNKNOWN | H9: Nie gwarantować całego wyniku; ujawnić prawa, wycenę i konflikt interesów.

Sheet Impact logic
A1: ID | B1: Rezultat | C1: Kontrfaktyczny wariant | D1: Baza | E1: Miara | F1: Źródło | G1: Ryzyka atrybucji / uwagi
A2: IMP-01 | B2: krótszy czas do testu | C2: obecny proces | D2: UNKNOWN | E2: dni/mediana | F2: UNKNOWN | G2: Wymagana metodologia dodatkowości; nie przypisywać całej obserwowanej zmiany programowi.
A3: IMP-02 | B3: odporność dostaw | C3: pojedynczy dostawca | D3: UNKNOWN | E3: % testowanej substytucji | F3: UNKNOWN | G3: Wymagana metodologia dodatkowości; nie przypisywać całej obserwowanej zmiany programowi.
A4: IMP-03 | B4: wartość dodana w Polsce | C4: import lub baza 2026 | D4: UNKNOWN | E4: mln PLN / % | F4: UNKNOWN | G4: Wymagana metodologia dodatkowości; nie przypisywać całej obserwowanej zmiany programowi.
A5: IMP-04 | B5: produktywność procesu cywilnego | C5: proces bez interwencji | D5: UNKNOWN | E5: wynik na nakład | F5: UNKNOWN | G5: Wymagana metodologia dodatkowości; nie przypisywać całej obserwowanej zmiany programowi.
A6: IMP-05 | B6: retencja kompetencji | C6: brak programu | D6: UNKNOWN | E6: % po 12/24 mies. | F6: UNKNOWN | G6: Wymagana metodologia dodatkowości; nie przypisywać całej obserwowanej zmiany programowi.
A7: IMP-06 | B7: wykonany eksport | C7: trend bazowy | D7: UNKNOWN | E7: przychód/marża/serwis | F7: UNKNOWN | G7: Wymagana metodologia dodatkowości; nie przypisywać całej obserwowanej zmiany programowi.
A8: IMP-07 | B8: uniknięte zobowiązania | C8: automatyczne skalowanie | D8: UNKNOWN | E8: mln PLN opcji niewykonanych | F8: UNKNOWN | G8: Wymagana metodologia dodatkowości; nie przypisywać całej obserwowanej zmiany programowi.

Sheet Sensitivity
A1: ID | B1: Czynnik | C1: Low | D1: Base | E1: High | F1: Jednostka | G1: Wpływ na decyzję | H1: Plan walidacji
A2: SEN-01 | B2: odchylenie CAPEX | F2: % | G2: do oceny | H2: właściciel i termin do wskazania
A3: SEN-02 | B3: opóźnienie uruchomienia | F3: miesiące | G3: do oceny | H3: właściciel i termin do wskazania
A4: SEN-03 | B4: wykorzystanie mocy | F4: % | G4: do oceny | H4: właściciel i termin do wskazania
A5: SEN-04 | B5: koszt finansowania | F5: % | G5: do oceny | H5: właściciel i termin do wskazania
A6: SEN-05 | B6: kurs walutowy | F6: PLN/waluta | G6: do oceny | H6: właściciel i termin do wskazania
A7: SEN-06 | B7: koszt serwisu i aktualizacji | F7: mln PLN | G7: do oceny | H7: właściciel i termin do wskazania
A8: SEN-07 | B8: retencja kadr | F8: % | G8: do oceny | H8: właściciel i termin do wskazania
A9: SEN-08 | B9: opóźnienie przychodu eksportowego | F9: miesiące | G9: do oceny | H9: właściciel i termin do wskazania
A10: SEN-09 | B10: udział projektów zamkniętych przed skalą | F10: % | G10: do oceny | H10: właściciel i termin do wskazania
A11: SEN-10 | B11: dostępność komponentów | F11: indeks | G11: do oceny | H11: właściciel i termin do wskazania

Sheet KPI
A1: ID | B1: Miernik | C1: Definicja | D1: Wartość bazowa | E1: Cel | F1: Jednostka | G1: Właściciel | H1: Źródło | I1: Guardrail / uwagi
A2: KPI-01 | B2: Czas do pilotażu | C2: mediana dni B0→kontrakt pilotażowy | D2: UNKNOWN | E2: UNKNOWN | F2: dni | G2: do wskazania | H2: UNKNOWN | I2: Cel nie może zostać zatwierdzony bez bazy, mianownika i kosztu pomiaru.
A3: KPI-02 | B3: Czas do testu użytkownika | C3: mediana dni B1→B3 | D3: UNKNOWN | E3: UNKNOWN | F3: dni | G3: do wskazania | H3: UNKNOWN | I3: Cel nie może zostać zatwierdzony bez bazy, mianownika i kosztu pomiaru.
A4: KPI-03 | B4: Udział testów użytkownika | C4: projekty z B3 / projekty po B2 | D4: UNKNOWN | E4: UNKNOWN | F4: % | G4: do wskazania | H4: UNKNOWN | I4: Cel nie może zostać zatwierdzony bez bazy, mianownika i kosztu pomiaru.
A5: KPI-04 | B5: Dyscyplina zamknięć | C5: zamknięte z powodem / decyzje końcowe | D5: UNKNOWN | E5: UNKNOWN | F5: % | G5: do wskazania | H5: UNKNOWN | I5: Cel nie może zostać zatwierdzony bez bazy, mianownika i kosztu pomiaru.
A6: KPI-05 | B6: Testowana substytucja | C6: elementy z testem / elementy krytyczne | D6: UNKNOWN | E6: UNKNOWN | F6: % | G6: do wskazania | H6: UNKNOWN | I6: Cel nie może zostać zatwierdzony bez bazy, mianownika i kosztu pomiaru.
A7: KPI-06 | B7: Pełny TCO | C7: koszt cyklu na jednostkę rezultatu | D7: UNKNOWN | E7: UNKNOWN | F7: mln PLN/jedn. | G7: do wskazania | H7: UNKNOWN | I7: Cel nie może zostać zatwierdzony bez bazy, mianownika i kosztu pomiaru.
A8: KPI-07 | B8: Retencja kadr | C8: osoby w roli po 12/24 mies. / absolwenci | D8: UNKNOWN | E8: UNKNOWN | F8: % | G8: do wskazania | H8: UNKNOWN | I8: Cel nie może zostać zatwierdzony bez bazy, mianownika i kosztu pomiaru.
A9: KPI-08 | B9: Wartość dodana w Polsce | C9: według zatwierdzonej metodologii | D9: UNKNOWN | E9: UNKNOWN | F9: mln PLN / % | G9: do wskazania | H9: UNKNOWN | I9: Cel nie może zostać zatwierdzony bez bazy, mianownika i kosztu pomiaru.
A10: KPI-09 | B10: Popyt po pilotażu | C10: kontynuacje z budżetu właściciela / pilotaże | D10: UNKNOWN | E10: UNKNOWN | F10: % | G10: do wskazania | H10: UNKNOWN | I10: Cel nie może zostać zatwierdzony bez bazy, mianownika i kosztu pomiaru.
A11: KPI-10 | B11: Wykonany eksport | C11: dostawy, przychód i serwis | D11: UNKNOWN | E11: UNKNOWN | F11: mln PLN | G11: do wskazania | H11: UNKNOWN | I11: Cel nie może zostać zatwierdzony bez bazy, mianownika i kosztu pomiaru.
